mongo_bulk/__init__.py
mongo_bulk-0.0.1.dist-info/LICENSE
mongo_bulk-0.0.1.dist-info/METADATA
mongo_bulk-0.0.1.dist-info/WHEEL
mongo_bulk-0.0.1.dist-info/top_level.txt
mongo_bulk-0.0.1.dist-info/RECORD
