Metadata-Version: 2.1
Name: mongo-bulk
Version: 0.0.1
Summary: mongo bulk
Home-page: https://github.com/pypa/sampleproject
Author: pw
Author-email: 891817163@qq.com
License: UNKNOWN
Platform: UNKNOWN
Classifier: Programming Language :: Python :: 3
Classifier: License :: OSI Approved :: MIT License
Classifier: Operating System :: OS Independent
Requires-Python: >=3.5
